{
  "timezone": "UTC",
  "start_time": "11:30",
  "interval_minutes": 40,
  "posts": [
    { "text": "REPLACE WITH POST 1 CAPTION", "image": "https://i.ibb.co/REPLACE-ME/banner1.jpg" },
    { "text": "REPLACE WITH POST 2 CAPTION", "image": "https://i.ibb.co/REPLACE-ME/banner2.jpg" },
    { "text": "REPLACE WITH POST 3 CAPTION", "image": "https://i.ibb.co/REPLACE-ME/banner3.jpg" },
    { "text": "REPLACE WITH POST 4 CAPTION", "image": "https://i.ibb.co/REPLACE-ME/banner4.jpg" },
    { "text": "REPLACE WITH POST 5 CAPTION", "image": "https://i.ibb.co/REPLACE-ME/banner5.jpg" },
    { "text": "REPLACE WITH POST 6 CAPTION", "image": "https://i.ibb.co/REPLACE-ME/banner6.jpg" },
    { "text": "REPLACE WITH POST 7 CAPTION", "image": "https://i.ibb.co/REPLACE-ME/banner7.jpg" },
    { "text": "REPLACE WITH POST 8 CAPTION", "image": "https://i.ibb.co/REPLACE-ME/banner8.jpg" },
    { "text": "REPLACE WITH POST 9 CAPTION", "image": "https://i.ibb.co/REPLACE-ME/banner9.jpg" },
    { "text": "REPLACE WITH POST 10 CAPTION", "image": "https://i.ibb.co/REPLACE-ME/banner10.jpg" }
  ]
}
